{
  "KoMa 92": {
    "displaytitle": "92. KoMa in Passau",
    "exists": "1",
    "fulltext": "KoMa 92",
    "fullurl": "https://de.komapedia.org/wiki/KoMa_92",
    "namespace": 0,
    "printouts": {
      "Anmeldung": [],
      "Beginn": [
        {
          "raw": "1/2025/6/18",
          "timestamp": "1750204800"
        }
      ],
      "Ende": [
        {
          "raw": "1/2025/6/22",
          "timestamp": "1750550400"
        }
      ],
      "Infoseite": [],
      "Ort": [
        "Passau"
      ]
    }
  },
  "KoMa 93": {
    "displaytitle": "93. KoMa in Chemnitz",
    "exists": "1",
    "fulltext": "KoMa 93",
    "fullurl": "https://de.komapedia.org/wiki/KoMa_93",
    "namespace": 0,
    "printouts": {
      "Anmeldung": [],
      "Beginn": [
        {
          "raw": "1/2025/10/29",
          "timestamp": "1761696000"
        }
      ],
      "Ende": [
        {
          "raw": "1/2025/11/2",
          "timestamp": "1762041600"
        }
      ],
      "Infoseite": [],
      "Ort": [
        "Chemnitz"
      ]
    }
  },
  "KoMa 94": {
    "displaytitle": "94. KoMa in Essen",
    "exists": "1",
    "fulltext": "KoMa 94",
    "fullurl": "https://de.komapedia.org/wiki/KoMa_94",
    "namespace": 0,
    "printouts": {
      "Anmeldung": [],
      "Beginn": [
        {
          "raw": "1/2026/5/1",
          "timestamp": "1777593600"
        }
      ],
      "Ende": [
        {
          "raw": "1/2026/5/31",
          "timestamp": "1780185600"
        }
      ],
      "Infoseite": [],
      "Ort": [
        "Essen"
      ]
    }
  }
}